eth_multirpc/__init__.py
eth_multirpc/async_multi_rpc_interface.py
eth_multirpc/base_multi_rpc_interface.py
eth_multirpc/constants.py
eth_multirpc/exceptions.py
eth_multirpc/gas_estimation.py
eth_multirpc/sync_multi_rpc_interface.py
eth_multirpc/tx_trace.py
eth_multirpc/utils.py
eth_multirpc-4.0.0.dist-info/METADATA
eth_multirpc-4.0.0.dist-info/WHEEL
eth_multirpc-4.0.0.dist-info/RECORD
