Metadata-Version: 2.3
Name: eth-multirpc
Version: 4.0.0
Summary: A robust Python library for interacting with Ethereum smart contracts via multiple RPC endpoints, ensuring reliability, availability, and load distribution with automatic retries on failure.
License: MIT
Keywords: eth,multirpc,web3
Author: MiKO
Author-email: mikoronjoo@gmail.com
Requires-Python: >=3.8,<4.0
Classifier: License :: OSI Approved :: MIT License
Classifier: Operating System :: OS Independent
Classifier: Programming Language :: Python :: 3
Classifier: Programming Language :: Python :: 3.8
Classifier: Programming Language :: Python :: 3.9
Classifier: Programming Language :: Python :: 3.10
Classifier: Programming Language :: Python :: 3.11
Classifier: Programming Language :: Python :: 3.12
Classifier: Programming Language :: Python :: 3.13
Requires-Dist: eth-account (>=0.13.0)
Requires-Dist: multicallable (>=7.0.0)
Requires-Dist: web3 (>=7.0.0,<8.0.0)
Project-URL: bugtracker, https://github.com/AXION-MONEY/eth-multirpc/issues
Project-URL: homepage, https://github.com/AXION-MONEY/eth-multirpc
